styledconsole/__init__.py
styledconsole/__main__.py
styledconsole/animation.py
styledconsole/columns.py
styledconsole/console.py
styledconsole/emoji_registry.py
styledconsole/emojis.py
styledconsole/enums.py
styledconsole/icons.py
styledconsole/policy.py
styledconsole/py.typed
styledconsole/table.py
styledconsole/types.py
styledconsole/builders/__init__.py
styledconsole/builders/banner.py
styledconsole/builders/base.py
styledconsole/builders/frame.py
styledconsole/builders/layout.py
styledconsole/builders/table.py
styledconsole/core/__init__.py
styledconsole/core/banner.py
styledconsole/core/box_mapping.py
styledconsole/core/context.py
styledconsole/core/export_manager.py
styledconsole/core/group.py
styledconsole/core/progress.py
styledconsole/core/registry.py
styledconsole/core/rendering_engine.py
styledconsole/core/styles.py
styledconsole/core/terminal_manager.py
styledconsole/core/theme.py
styledconsole/data/colors.py
styledconsole/data/palettes.json
styledconsole/data/palettes.py
styledconsole/declarative/__init__.py
styledconsole/declarative/facade.py
styledconsole/declarative/jinja.py
styledconsole/declarative/loader.py
styledconsole/declarative/shorthand.py
styledconsole/declarative/templates.py
styledconsole/effects/__init__.py
styledconsole/effects/engine.py
styledconsole/effects/registry.py
styledconsole/effects/resolver.py
styledconsole/effects/spec.py
styledconsole/effects/strategies.py
styledconsole/export/__init__.py
styledconsole/export/config.py
styledconsole/export/emoji_parser.py
styledconsole/export/emoji_renderer.py
styledconsole/export/emoji_sources.py
styledconsole/export/font_loader.py
styledconsole/export/image_cropper.py
styledconsole/export/image_exporter.py
styledconsole/export/image_theme.py
styledconsole/export/fonts/LICENSE
styledconsole/model/__init__.py
styledconsole/model/base.py
styledconsole/model/objects.py
styledconsole/model/registry.py
styledconsole/presets/__init__.py
styledconsole/presets/dashboard.py
styledconsole-0.10.4.dist-info/METADATA
styledconsole-0.10.4.dist-info/WHEEL
styledconsole-0.10.4.dist-info/entry_points.txt
styledconsole-0.10.4.dist-info/licenses/LICENSE
styledconsole-0.10.4.dist-info/RECORD
