Metadata-Version: 2.4
Name: styledconsole
Version: 0.10.4
Summary: A modern Python library for elegant terminal output with rich formatting, colors, emoji support, and export capabilities
Project-URL: Homepage, https://github.com/ksokolowski/StyledConsole
Project-URL: Repository, https://github.com/ksokolowski/StyledConsole
Project-URL: Documentation, https://github.com/ksokolowski/StyledConsole
Author-email: Krzysztof Sokołowski <styledconsole@proton.me>
License: Apache-2.0
License-File: LICENSE
Keywords: cli,colors,console,emoji,formatting,terminal,tui
Classifier: Development Status :: 5 - Production/Stable
Classifier: Intended Audience :: Developers
Classifier: License :: OSI Approved :: Apache Software License
Classifier: Programming Language :: Python :: 3
Classifier: Programming Language :: Python :: 3.10
Classifier: Programming Language :: Python :: 3.11
Classifier: Programming Language :: Python :: 3.12
Classifier: Programming Language :: Python :: 3.13
Classifier: Programming Language :: Python :: 3.14
Classifier: Topic :: Software Development :: Libraries :: Python Modules
Classifier: Topic :: Terminals
Requires-Python: >=3.10
Requires-Dist: ansi2html>=1.8.0
Requires-Dist: emoji>=2.15.0
Requires-Dist: pyfiglet>=1.0.2
Requires-Dist: rich>=13.7
Requires-Dist: typing-extensions>=4.0.0
Requires-Dist: wcwidth>=0.2.13
Provides-Extra: all
Requires-Dist: jinja2>=3.0; extra == 'all'
Requires-Dist: pillow>=10.0.0; extra == 'all'
Requires-Dist: pyyaml>=6.0; extra == 'all'
Provides-Extra: image
Requires-Dist: pillow>=10.0.0; extra == 'image'
Provides-Extra: jinja
Requires-Dist: jinja2>=3.0; extra == 'jinja'
Provides-Extra: yaml
Requires-Dist: pyyaml>=6.0; extra == 'yaml'
